thinky/__init__.py
thinky/foo.py
thinky-0.0.3.dist-info/METADATA
thinky-0.0.3.dist-info/WHEEL
thinky-0.0.3.dist-info/RECORD
