Metadata-Version: 2.4
Name: thinky
Version: 0.0.3
Summary: thinky makes your AI models smarter
Project-URL: Homepage, https://nlile.github.io/thinky/
Project-URL: Repository, https://github.com/nlile/thinky
Project-URL: Documentation, https://nlile.github.io/thinky/
Author-email: nlile <7707104+nlile@users.noreply.github.com>
Keywords: python
Classifier: Intended Audience :: Developers
Classifier: Programming Language :: Python
Classifier: Programming Language :: Python :: 3
Classifier: Programming Language :: Python :: 3.10
Classifier: Programming Language :: Python :: 3.11
Classifier: Programming Language :: Python :: 3.12
Classifier: Programming Language :: Python :: 3.13
Classifier: Programming Language :: Python :: 3.14
Classifier: Topic :: Software Development :: Libraries :: Python Modules
Requires-Python: <4.0,>=3.10
